.coveragerc
.gitignore
.pylintrc
.readthedocs.yml
.travis.yml
CHANGELOG.md
LICENSE
Makefile
README.md
pytest.ini
setup.py
docs/Makefile
docs/make.bat
docs/source/concepts.rst
docs/source/conf.py
docs/source/index.rst
docs/source/license.rst
docs/source/policy_language.rst
docs/source/_static/.keep
docs/source/_templates/.keep
docs/source/components/components.rst
docs/source/components/context.rst
docs/source/components/pdp.rst
docs/source/components/policy.rst
docs/source/components/provider.rst
docs/source/components/request.rst
docs/source/components/storage.rst
docs/source/components/backends/file.rst
docs/source/components/backends/memory.rst
docs/source/components/backends/mongo.rst
docs/source/components/backends/redis.rst
docs/source/components/backends/sql.rst
docs/source/modules/modules.rst
docs/source/modules/py_abac.policy.conditions.attribute.rst
docs/source/modules/py_abac.policy.conditions.collection.rst
docs/source/modules/py_abac.policy.conditions.logic.rst
docs/source/modules/py_abac.policy.conditions.numeric.rst
docs/source/modules/py_abac.policy.conditions.object.rst
docs/source/modules/py_abac.policy.conditions.others.rst
docs/source/modules/py_abac.policy.conditions.rst
docs/source/modules/py_abac.policy.conditions.string.rst
docs/source/modules/py_abac.policy.rst
docs/source/modules/py_abac.provider.rst
docs/source/modules/py_abac.rst
docs/source/modules/py_abac.storage.file.rst
docs/source/modules/py_abac.storage.memory.rst
docs/source/modules/py_abac.storage.mongo.rst
docs/source/modules/py_abac.storage.redis.rst
docs/source/modules/py_abac.storage.rst
docs/source/modules/py_abac.storage.sql.rst
examples/__init__.py
examples/example_1.py
examples/example_2.py
py_abac/__init__.py
py_abac/context.py
py_abac/exceptions.py
py_abac/pdp.py
py_abac/request.py
py_abac/version.py
py_abac.egg-info/PKG-INFO
py_abac.egg-info/SOURCES.txt
py_abac.egg-info/dependency_links.txt
py_abac.egg-info/requires.txt
py_abac.egg-info/top_level.txt
py_abac/policy/__init__.py
py_abac/policy/policy.py
py_abac/policy/rules.py
py_abac/policy/targets.py
py_abac/policy/conditions/__init__.py
