Metadata-Version: 2.1
Name: py-abac
Version: 0.4.1
Summary: Attribute-based access control (ABAC)
Home-page: https://github.com/ketgo/py-abac
Author: Ketan Goyal
Author-email: ketangoyal1988@gmail.com
License: Apache 2.0 license
Keywords: ACL ABAC access-control policy security authorization permission
Platform: UNKNOWN
Classifier: Intended Audience :: Developers
Classifier: License :: OSI Approved :: Apache Software License
Classifier: Operating System :: OS Independent
Classifier: Topic :: System :: Systems Administration
Classifier: Topic :: System :: Networking
Classifier: Topic :: System :: Networking :: Firewalls
Classifier: Topic :: Security
Classifier: Topic :: Software Development
Classifier: Topic :: Utilities
Classifier: Natural Language :: English
Classifier: Programming Language :: Python
Classifier: Programming Language :: Python :: 3.5
Classifier: Programming Language :: Python :: 3.6
Classifier: Programming Language :: Python :: 3.7
Classifier: Programming Language :: Python :: Implementation :: PyPy
Requires-Python: >3.4
Provides-Extra: file
Provides-Extra: sql
Provides-Extra: redis
Provides-Extra: mongo
Provides-Extra: doc
Provides-Extra: dev
